DagLpDp/DP.py
DagLpDp/__init__.py
DagLpDp-1.2.dist-info/LICENSE
DagLpDp-1.2.dist-info/METADATA
DagLpDp-1.2.dist-info/WHEEL
DagLpDp-1.2.dist-info/top_level.txt
DagLpDp-1.2.dist-info/RECORD
