Metadata-Version: 2.1
Name: DagLpDp
Version: 1.2
Summary: 用动态规划求解有向无环图的最长路径问题
Home-page: https://github.com/wangwenhao-DATA-OG/DagLpDp
Author: 王文皓(wangwenhao)
Author-email: DATA-OG@139.com
License: UNKNOWN
Platform: UNKNOWN
Classifier: Programming Language :: Python :: 3
Classifier: License :: OSI Approved :: Apache Software License
Classifier: Operating System :: OS Independent
Requires-Python: >=3.0
License-File: LICENSE
